[
  {
    "filing_folder": "0000354950-13-000015",
    "net_sales": "$19,124",
    "fiscal_ending_date": "May 5, 2013"
  },
  {
    "filing_folder": "0000354950-13-000032",
    "net_sales": "$22,522",
    "fiscal_ending_date": "August 4, 2013"
  },
  {
    "filing_folder": "0000354950-13-000047",
    "net_sales": "$19,470",
    "fiscal_ending_date": "November 3, 2013"
  },
  {
    "filing_folder": "0000354950-14-000017",
    "net_sales": "$19,687",
    "fiscal_ending_date": "May 4, 2014"
  },
  {
    "filing_folder": "0000354950-14-000032",
    "net_sales": "$23,811",
    "fiscal_ending_date": "August 3, 2014"
  },
  {
    "filing_folder": "0000354950-14-000047",
    "net_sales": "$20,516",
    "fiscal_ending_date": "November 2, 2014"
  },
  {
    "filing_folder": "0000354950-15-000018",
    "net_sales": "$20,891",
    "fiscal_ending_date": "May 3, 2015"
  },
  {
    "filing_folder": "0000354950-15-000033",
    "net_sales": "$24,829",
    "fiscal_ending_date": "August 2, 2015"
  },
  {
    "filing_folder": "0000354950-15-000049",
    "net_sales": "$21,819",
    "fiscal_ending_date": "November 1, 2015"
  },
  {
    "filing_folder": "0000354950-16-000065",
    "net_sales": "$22,762",
    "fiscal_ending_date": "May 1, 2016"
  },
  {
    "filing_folder": "0000354950-16-000082",
    "net_sales": "$26,472",
    "fiscal_ending_date": "July 31, 2016"
  },
  {
    "filing_folder": "0000354950-16-000094",
    "net_sales": "$23,154",
    "fiscal_ending_date": "October 30, 2016"
  },
  {
    "filing_folder": "0000354950-17-000014",
    "net_sales": "$23,887",
    "fiscal_ending_date": "April 30, 2017"
  },
  {
    "filing_folder": "0000354950-17-000032",
    "net_sales": "$28,108",
    "fiscal_ending_date": "July 30, 2017"
  },
  {
    "filing_folder": "0000354950-17-000046",
    "net_sales": "$25,026",
    "fiscal_ending_date": "October 29, 2017"
  },
  {
    "filing_folder": "0000354950-18-000034",
    "net_sales": "$24,947",
    "fiscal_ending_date": "April 29, 2018"
  },
  {
    "filing_folder": "0000354950-18-000051",
    "net_sales": "$30,463",
    "fiscal_ending_date": "July 29, 2018"
  },
  {
    "filing_folder": "0000354950-18-000065",
    "net_sales": "$26,302",
    "fiscal_ending_date": "October 28, 2018"
  },
  {
    "filing_folder": "0000354950-19-000024",
    "net_sales": "$26,381",
    "fiscal_ending_date": "May 5, 2019"
  },
  {
    "filing_folder": "0000354950-19-000057",
    "net_sales": "$30,839",
    "fiscal_ending_date": "August 4, 2019"
  },
  {
    "filing_folder": "0000354950-19-000066",
    "net_sales": "$27,223",
    "fiscal_ending_date": "November 3, 2019"
  },
  {
    "filing_folder": "0000354950-20-000041",
    "net_sales": "$28,260",
    "fiscal_ending_date": "May 3, 2020"
  },
  {
    "filing_folder": "0000354950-20-000068",
    "net_sales": "$38,053",
    "fiscal_ending_date": "August 2, 2020"
  },
  {
    "filing_folder": "0000354950-20-000103",
    "net_sales": "$33,536",
    "fiscal_ending_date": "November 1, 2020"
  },
  {
    "filing_folder": "0000354950-21-000147",
    "net_sales": "$37,500",
    "fiscal_ending_date": "May 2, 2021"
  },
  {
    "filing_folder": "0000354950-21-000189",
    "net_sales": "$41,118",
    "fiscal_ending_date": "August 1, 2021"
  },
  {
    "filing_folder": "0000354950-21-000234",
    "net_sales": "$36,820",
    "fiscal_ending_date": "October 31, 2021"
  },
  {
    "filing_folder": "0000354950-22-000158",
    "net_sales": "$38,908",
    "fiscal_ending_date": "May 1, 2022"
  },
  {
    "filing_folder": "0000354950-22-000193",
    "net_sales": "$43,792",
    "fiscal_ending_date": "July 31, 2022"
  },
  {
    "filing_folder": "0000354950-22-000239",
    "net_sales": "$38,872",
    "fiscal_ending_date": "October 30, 2022"
  },
  {
    "filing_folder": "0000354950-23-000144",
    "net_sales": "$37,257",
    "fiscal_ending_date": "April 30, 2023"
  },
  {
    "filing_folder": "0000354950-23-000185",
    "net_sales": "$42,916",
    "fiscal_ending_date": "July 30, 2023"
  },
  {
    "filing_folder": "0000354950-23-000240",
    "net_sales": "$37,710",
    "fiscal_ending_date": "October 29, 2023"
  },
  {
    "filing_folder": "0000354950-24-000152",
    "net_sales": "$36,418",
    "fiscal_ending_date": "April 28, 2024"
  },
  {
    "filing_folder": "0000354950-24-000201",
    "net_sales": "$43,175",
    "fiscal_ending_date": "July 28, 2024"
  },
  {
    "filing_folder": "0000354950-24-000240",
    "net_sales": "$40,217",
    "fiscal_ending_date": "October 27, 2024"
  }
]